Metadata-Version: 2.1
Name: date-extractor
Version: 3.9.1
Summary: Extract dates from text
Home-page: https://github.com/DanielJDufour/date-extractor
Author: Daniel J. Dufour
Author-email: daniel.j.dufour@gmail.com
License: UNKNOWN
Project-URL: Source, https://github.com/DanielJDufour/date-extractor
Project-URL: Tracker, https://github.com/DanielJDufour/date-extractor/issues
Keywords: data datetime extraction python tagging
Platform: UNKNOWN
Classifier: Programming Language :: Python :: 3
Classifier: License :: OSI Approved :: Apache Software License
Classifier: Operating System :: OS Independent
Classifier: Development Status :: 6 - Mature
Classifier: Intended Audience :: Developers
Classifier: Natural Language :: English
Requires-Dist: pytz
